README.md
setup.cfg
setup.py
./SIPSim/DiffusionCython.c
./SIPSim/IsoIncorpCython.c
./SIPSim/QSIPCython.c
SIPSim/BD_Shift.py
SIPSim/CommTable.py
SIPSim/Config.py
SIPSim/DeltaBD.py
SIPSim/DiffBoundLayer.py
SIPSim/Diffusion.py
SIPSim/Error_Dist.py
SIPSim/FigGen.py
SIPSim/FracTable.py
SIPSim/Fractions.py
SIPSim/FragGC.py
SIPSim/Frag_MultiKDE.py
SIPSim/Fragments.py
SIPSim/Genome.py
SIPSim/Genome_Download.py
SIPSim/HR_SIP.py
SIPSim/IndexGenomes.py
SIPSim/IsoIncorp.py
SIPSim/OTU_Table.py
SIPSim/OrderedSet.py
SIPSim/PCR.py
SIPSim/QSIP.py
SIPSim/QSIP_atomExcess.py
SIPSim/SimComms.py
SIPSim/SimFrags.py
SIPSim/TraitEvo.py
SIPSim/Utils.py
SIPSim/__init__.py
SIPSim/__main__.py
SIPSim/rtnorm.py
SIPSim/skew_normal.py
SIPSim.egg-info/PKG-INFO
SIPSim.egg-info/SOURCES.txt
SIPSim.egg-info/dependency_links.txt
SIPSim.egg-info/entry_points.txt
SIPSim.egg-info/requires.txt
SIPSim.egg-info/top_level.txt
SIPSim/Commands/BD_Shift.py
SIPSim/Commands/Communities.py
SIPSim/Commands/DBL.py
SIPSim/Commands/DeltaBD.py
SIPSim/Commands/Diffusion.py
SIPSim/Commands/Fragment_KDE.py
SIPSim/Commands/Fragment_KDE_cat.py
SIPSim/Commands/Fragment_parse.py
SIPSim/Commands/Fragments.py
SIPSim/Commands/Genome_download.py
SIPSim/Commands/Genome_index.py
SIPSim/Commands/Genome_rename.py
SIPSim/Commands/Gradient_fractions.py
SIPSim/Commands/HRSIP.py
SIPSim/Commands/IncorpConfigExample.py
SIPSim/Commands/Isotope_incorp.py
SIPSim/Commands/KDE_bandwidth.py
SIPSim/Commands/KDE_info.py
SIPSim/Commands/KDE_parse.py
SIPSim/Commands/KDE_plot.py
SIPSim/Commands/KDE_sample.py
SIPSim/Commands/KDE_selectTaxa.py
SIPSim/Commands/OTU_PCR.py
SIPSim/Commands/OTU_add_error.py
SIPSim/Commands/OTU_sampleData.py
SIPSim/Commands/OTU_subsample.py
SIPSim/Commands/OTU_sum.py
SIPSim/Commands/OTU_table.py
SIPSim/Commands/OTU_wideLong.py
SIPSim/Commands/Tree_sim.py
SIPSim/Commands/__init__.py
SIPSim/Commands/qSIP.py
SIPSim/Commands/qSIP_atomExcess.py