Metadata-Version: 1.0
Name: SIPSim
Version: 0.3.0
Summary: Simulate High Resolution Stable Isotope Probing Datasets
Home-page: https://github.com/nick-youngblut/SIPSim
Author: Nick Youngblut
Author-email: nyoungb2@gmail.com
License: MIT license
Platform: UNKNOWN
